{
  "data": {
    "organisation": [
      {
        "name": "The Big Bank Organisation",
        "companies": [
        	{
	            "name": "The Big Bank Company",
	            "cnpjNumber": "12345678901234",
	            "businessInvoiceFinancing":[
	            	{
	            		"type": "Desconto de Duplicata",
	            		"fees":[
	            			{
	            				"serviceName": "Renovacao Contratual",
	            			    "serviceCode": "RC",
	            			    "chargeTriggerInfo": "Fatores geradores da taxa",
	            			    "maxPrice": "500",
	            			    "currency": "BRL"
	            			},
	            			{
	            				"serviceName": "Taxa de Cadastro",
	            			    "serviceCode": "TC",
	            			    "chargeTriggerInfo": "Fatores geradores da taxa",
	            			    "maxPrice": "500",
	            			    "currency": "BRL"
	            			}
	            		],
	            		"interestRates": [
	            			{
	            				"rate": "10",
	            				"referencialRate": null,
	            				"indexer": "CDI",
	            				"prePostTax": "POS",
	            				"frequency": "a.m.",
	            				"incomeRateInfo": "Informações adicionais do calculo de juros"
	            			}
	            		],
	            		"requiredWarranties":[
	            			"Caução",
	            			"Penhor",
	            			"Alienação Fiduciária"
		            	],
		            	"termsCondictions": "Lista dos termos em texto livre ou URL de indicação das condições"
	            	}
	            ]
        	}
        ]
      }
    ]
  },
  "links": {
    "self": "https://api.banco.com.br/open-banking/channels/v1/electronic-channels",
    "first": "https://api.banco.com.br/open-banking/channels/v1/electronic-channels",
    "prev": null,
    "next": null,
    "last": "https://api.banco.com.br/open-banking/channels/v1/electronic-channels"
  },
  "meta": {
    "totalRecords": 1,
    "totalPages": 1
  }
}